{
  "version": 1,
  "active": true,
  "skill": "ralplan",
  "phase": "architect",
  "updated_at": "2026-06-13T03:35:06.669Z",
  "active_skills": [
    {
      "skill": "ralplan",
      "phase": "architect",
      "active": true,
      "activated_at": "2026-06-13T03:35:06.669Z",
      "updated_at": "2026-06-13T03:35:06.669Z",
      "hud": {
        "version": 1,
        "summary": "persisted architect stage 3",
        "chips": [
          {
            "label": "stage",
            "value": "architect",
            "priority": 10
          },
          {
            "label": "iter",
            "value": "3",
            "priority": 30
          }
        ],
        "updated_at": "2026-06-13T03:35:06.667Z"
      }
    }
  ],
  "active_subskills": []
}
